gtf2seq.py
gtf2seq-0.1.0.data/scripts/gtf2seq.py
gtf2seq-0.1.0.dist-info/METADATA
gtf2seq-0.1.0.dist-info/WHEEL
gtf2seq-0.1.0.dist-info/top_level.txt
gtf2seq-0.1.0.dist-info/RECORD
