Metadata-Version: 2.1
Name: gtf2seq
Version: 0.1.0
Summary: Extract genomic sequences and visualize the genomic features in word document
Home-page: UNKNOWN
Author: Bix
Author-email: bix0032@gmail.com
License: MIT
Platform: UNKNOWN
Classifier: Topic :: Scientific/Engineering :: Bio-Informatics
Classifier: Programming Language :: Python :: 3
Requires-Dist: python-docx (==0.8.10)
Requires-Dist: PyVCF (==0.6.8)
Requires-Dist: pyfaidx
